[
  {
    "panel": "Oporto",
    "mensajes": 530
  },
  {
    "panel": "GoatGaming",
    "mensajes": 359
  },
  {
    "panel": "Godzilla",
    "mensajes": 307
  },
  {
    "panel": "Cocan",
    "mensajes": 248
  },
  {
    "panel": "BT300",
    "mensajes": 224
  },
  {
    "panel": "VGanamos",
    "mensajes": 212
  },
  {
    "panel": "SimonP",
    "mensajes": 208
  },
  {
    "panel": "Venecia",
    "mensajes": 200
  },
  {
    "panel": "Red",
    "mensajes": 177
  },
  {
    "panel": "Rotterdam",
    "mensajes": 176
  },
  {
    "panel": "ThiagoP",
    "mensajes": 170
  },
  {
    "panel": "Miami",
    "mensajes": 160
  },
  {
    "panel": "Cokesin",
    "mensajes": 151
  },
  {
    "panel": "Luck",
    "mensajes": 131
  },
  {
    "panel": "Dragon",
    "mensajes": 127
  },
  {
    "panel": "Open24hs",
    "mensajes": 114
  },
  {
    "panel": "Escaloneta",
    "mensajes": 110
  },
  {
    "panel": "Detager",
    "mensajes": 91
  },
  {
    "panel": "Raven",
    "mensajes": 64
  },
  {
    "panel": "Somos",
    "mensajes": 49
  },
  {
    "panel": "300Vip",
    "mensajes": 0
  },
  {
    "panel": "Fort99",
    "mensajes": 0
  },
  {
    "panel": "Royal",
    "mensajes": 0
  },
  {
    "panel": "PubliW",
    "mensajes": 0
  }
]