[
  {
    "panel": "Oporto",
    "mensajes": 261
  },
  {
    "panel": "BT300",
    "mensajes": 237
  },
  {
    "panel": "VGanamos",
    "mensajes": 231
  },
  {
    "panel": "Miami",
    "mensajes": 206
  },
  {
    "panel": "Luck",
    "mensajes": 193
  },
  {
    "panel": "Jota",
    "mensajes": 181
  },
  {
    "panel": "SimonP",
    "mensajes": 177
  },
  {
    "panel": "Raven",
    "mensajes": 166
  },
  {
    "panel": "Red",
    "mensajes": 145
  },
  {
    "panel": "Godzilla",
    "mensajes": 142
  },
  {
    "panel": "GoatGaming",
    "mensajes": 140
  },
  {
    "panel": "ThiagoP",
    "mensajes": 139
  },
  {
    "panel": "Cokesin",
    "mensajes": 126
  },
  {
    "panel": "Cocan",
    "mensajes": 117
  },
  {
    "panel": "Somos",
    "mensajes": 113
  },
  {
    "panel": "RedTrebol",
    "mensajes": 110
  },
  {
    "panel": "Venecia",
    "mensajes": 108
  },
  {
    "panel": "Open24hs",
    "mensajes": 103
  },
  {
    "panel": "Detager",
    "mensajes": 65
  },
  {
    "panel": "Sin Asignar",
    "mensajes": 52
  },
  {
    "panel": "Publi CYBER",
    "mensajes": 48
  },
  {
    "panel": "300Vip",
    "mensajes": 0
  }
]